[
	{
		"name": "bojautologin",
		"value": "02b96e0719bc8db2811a474ca7112e84e820a51c",
		"path": "/",
		"domain": ".acmicpc.net",
		"secure": true,
		"expiry": 1694264525
	},
	{
		"name": "_fbp",
		"value": "fb.1.1693659682771.1734237824",
		"path": "/",
		"domain": ".acmicpc.net",
		"secure": false,
		"expiry": 1701435726
	},
	{
		"name": "_ga",
		"value": "GA1.1.711691773.1693659682",
		"path": "/",
		"domain": ".acmicpc.net",
		"secure": false,
		"expiry": 1728219725
	},
	{
		"name": "_ga_C81GGQEMJZ",
		"value": "GS1.1.1693659682.1.1.1693659725.0.0.0",
		"path": "/",
		"domain": ".acmicpc.net",
		"secure": false,
		"expiry": 1728219725
	},
	{
		"name": "OnlineJudge",
		"value": "llfhovf8q2ttrkuumfaqp407og",
		"path": "/",
		"domain": ".acmicpc.net",
		"secure": true,
		"expiry": 0
	}
]